GPTX/__init__.py
GPTX/main.py
gptx-0.0.1.dist-info/METADATA
gptx-0.0.1.dist-info/WHEEL
gptx-0.0.1.dist-info/licenses/LICENSE
gptx-0.0.1.dist-info/RECORD
