Metadata-Version: 2.1
Name: GPTX
Version: 0.0.1
Summary: GPTX eXtension Library
Project-URL: GitHub, https://github.com/jamesburchill/GPTX
Project-URL: Bug Tracker, https://github.com/jamesburchill/GPTX/issues
Author-email: "James C. Burchill" <pypi@jcb.dev>
License-File: LICENSE
Classifier: License :: OSI Approved :: MIT License
Classifier: Operating System :: OS Independent
Classifier: Programming Language :: Python :: 3
Requires-Python: >=3.7
